fcatng/__init__.py
fcatng/compare_context.py
fcatng/concept.py
fcatng/concept_lattice.py
fcatng/concept_system.py
fcatng/context.py
fcatng/implication.py
fcatng/mvcontext.py
fcatng/partial_context.py
fcatng/scale.py
fcatng/algorithms/__init__.py
fcatng/algorithms/aibasis.py
fcatng/algorithms/closure_operators.py
fcatng/algorithms/conceptual_exploration.py
fcatng/algorithms/covering_relation.py
fcatng/algorithms/dg_basis.py
fcatng/algorithms/dg_basistest.py
fcatng/algorithms/exploration.py
fcatng/algorithms/explorationtest.py
fcatng/algorithms/filters.py
fcatng/algorithms/implication_covers.py
fcatng/algorithms/norris.py
fcatng/algorithms/scaling.py
fcatng/algorithms/exploration/__init__.py
fcatng/algorithms/exploration/exploration.py
fcatng/algorithms/exploration/explorationtest.py
fcatng/algorithms/exploration/examples/bi_unars.py
fcatng/algorithms/exploration2/__init__.py
fcatng/algorithms/exploration2/exploration.py
fcatng/algorithms/exploration2/explorationtest.py
fcatng/algorithms/exploration2/examples/numbers.py
fcatng/readwrite/__init__.py
fcatng/readwrite/comma_separated.py
fcatng/readwrite/cxt.py
fcatng/readwrite/dot.py
fcatng/readwrite/fimi.py
fcatng/readwrite/tab_separated.py
fcatng/readwrite/xml_.py
fcatng-0.0.8.dist-info/LICENSE
fcatng-0.0.8.dist-info/METADATA
fcatng-0.0.8.dist-info/WHEEL
fcatng-0.0.8.dist-info/top_level.txt
fcatng-0.0.8.dist-info/RECORD
