Metadata-Version: 2.1
Name: fcatng
Version: 0.0.8
Summary: An attempt to revive the fca package by ae-hse.
Author-email: Tom Hanika <tomhanika@algebra20.de>
Project-URL: Homepage, https://github.com/tomhanika/fcatng
Project-URL: Issues, https://github.com/tomhanika/fcatng/issues
Classifier: Programming Language :: Python :: 3
Classifier: License :: OSI Approved :: MIT License
Classifier: Operating System :: OS Independent
Requires-Python: >=3.10
License-File: LICENSE
